imglite/__init__.py
imglite/cli.py
imglite-0.0.6.dist-info/METADATA
imglite-0.0.6.dist-info/WHEEL
imglite-0.0.6.dist-info/entry_points.txt
imglite-0.0.6.dist-info/top_level.txt
imglite-0.0.6.dist-info/RECORD
