Metadata-Version: 2.1
Name: imglite
Version: 0.0.6
Summary: A SQLite-based multi-image storage specification and associated utilities.
Requires-Python: >=3.8
Requires-Dist: tqdm>=4.67.1
